frogress/__init__.py
frogress/api.py
frogress/bars.py
frogress/humanize.py
frogress/utils.py
frogress/widgets.py
frogress/tests/__init__.py
frogress/tests/test_api.py
frogress/tests/test_bars.py
frogress/tests/test_humanize.py
frogress/tests/test_main.py
frogress/tests/test_utils.py
frogress/tests/test_widgets.py
frogress-0.10.1.dist-info/LICENSE
frogress-0.10.1.dist-info/METADATA
frogress-0.10.1.dist-info/WHEEL
frogress-0.10.1.dist-info/top_level.txt
frogress-0.10.1.dist-info/RECORD
