Metadata-Version: 2.1
Name: frogress
Version: 0.10.1
Summary: A progress tool for humans
Home-page: https://github.com/lukaszb/frogress
Author: Lukasz Balcerzak
Author-email: lukaszbalcerzak@gmail.com
License: MIT
Classifier: Development Status :: 4 - Beta
Classifier: License :: OSI Approved :: MIT License
Classifier: Intended Audience :: Developers
Classifier: Operating System :: OS Independent
Classifier: Programming Language :: Python
Classifier: Programming Language :: Python :: 3
License-File: LICENSE
